mini_des-0.1.0.dist-info/licenses/LICENSE.txt
minides/__init__.py
minides/core/__init__.py
minides/core/min_heap.py
minides/core/simulation_engine.py
mini_des-0.1.0.dist-info/METADATA
mini_des-0.1.0.dist-info/WHEEL
mini_des-0.1.0.dist-info/top_level.txt
mini_des-0.1.0.dist-info/RECORD
