Metadata-Version: 2.4
Name: mini-des
Version: 0.1.0
Summary: A minimalist, agent-based discrete event simulation engine in Python.
Author-email: littleqjy <littleqjy@gmail.com>
License-Expression: MIT
Project-URL: Homepage, https://github.com/littleQiu22/minimalist-discrete-event-simulation-engine
Classifier: Programming Language :: Python :: 3
Classifier: Operating System :: OS Independent
Classifier: Intended Audience :: Developers
Classifier: Intended Audience :: Science/Research
Classifier: Topic :: Scientific/Engineering
Requires-Python: >=3.9
License-File: LICENSE.txt
Dynamic: license-file
